agent_cli_tool/__init__.py
agent_cli_tool/agents/__init__.py
agent_cli_tool/agents/agent.py
agent_cli_tool/agents/ai.py
agent_cli_tool/cli/__init__.py
agent_cli_tool/cli/cli.py
agent_cli_tool/config/__init__.py
agent_cli_tool/config/config.py
agent_cli_tool/plugins/__init__.py
agent_cli_tool/plugins/fetch.py
agent_cli_tool/plugins/file.py
agent_cli_tool/plugins/shell.py
agent_cli_tool/ui/__init__.py
agent_cli_tool/ui/base.py
agent_cli_tool/ui/rich.py
agent_cli_tool/ui/stdout.py
agent_cli_tool/ui/tui.py
agent_cli_tool-0.2.2.dist-info/METADATA
agent_cli_tool-0.2.2.dist-info/WHEEL
agent_cli_tool-0.2.2.dist-info/entry_points.txt
agent_cli_tool-0.2.2.dist-info/RECORD
