Metadata-Version: 2.4
Name: agent-cli-tool
Version: 0.2.2
Summary: Ask openai on your terminal
Author-email: woodwhale <Awoodwhale@gmail.com>
Requires-Python: >=3.10
Requires-Dist: openai>=1.75.0
Requires-Dist: python-dotenv>=1.1.0
Requires-Dist: requests>=2.32.3
Requires-Dist: rich>=14.0.0
Requires-Dist: textual>=6.11.0
Requires-Dist: wcwidth>=0.2.14
